TN_code/__init__.py
TN_code/fourier/__init__.py
TN_code/fourier/fourier_coeff.py
TN_code/fourier/fourier_complex.py
TN_code/hardware/__init__.py
TN_code/hardware/get_data.py
TN_code/hardware/lees_data_numpy.py
TN_code/hardware/write_data.py
TN_code/plotten/TISTNplot.py
TN_code/plotten/__init__.py
TN_code-1.4.dist-info/LICENSE
TN_code-1.4.dist-info/METADATA
TN_code-1.4.dist-info/WHEEL
TN_code-1.4.dist-info/top_level.txt
TN_code-1.4.dist-info/RECORD
