Metadata-Version: 2.1
Name: TN-code
Version: 1.4
Summary: Code gebruikt bij de opleiding TN van de Haagse Hogeschool
Home-page: https://hhs-tn.github.io
Author: Derek Land
Author-email: d.d.land@hhs.nl
License: MIT
Classifier: License :: OSI Approved :: MIT License
Classifier: Natural Language :: Dutch
Classifier: Programming Language :: Python :: 3
Classifier: Topic :: Utilities
License-File: LICENSE
Requires-Dist: numpy
Requires-Dist: matplotlib
Requires-Dist: pandas
Requires-Dist: sympy
